[
  {
    "title": "Clinical Counselling and Mental Health Support Services",
    "organization": "Saskatchewan Public Safety Agency",
    "published_date": "2026/03/26",
    "closing_date": "2026/04/22",
    "link": "https://www.merx.com/public/supplier/interception/view-notice/443941271808?origin=0",
    "page": 1,
    "scraped_at": "2026-03-28T11:33:03.018747"
  },
  {
    "title": "Fort Smith Health Center Chiller Replacement",
    "organization": "Northwest Territories, NT, CAN",
    "published_date": "2026/03/24",
    "closing_date": "2026/04/17",
    "link": "https://www.merx.com/public/supplier/interception/view-notice/22785000446?origin=0",
    "page": 1,
    "scraped_at": "2026-03-28T11:33:03.045028"
  },
  {
    "title": "Health Centre Renovation Coral Harbour, NU",
    "organization": "Government of Nunavut",
    "published_date": "2026/03/24",
    "closing_date": "2026/04/10",
    "link": "https://www.merx.com/public/supplier/interception/view-notice/443937112370?origin=0",
    "page": 1,
    "scraped_at": "2026-03-28T11:33:03.125109"
  },
  {
    "title": "Unmanned Ground Vehicle for Canadian Forces Health Services",
    "organization": "Department of National Defence (DND)",
    "published_date": "2026/03/23",
    "closing_date": "2026/04/17",
    "link": "https://www.merx.com/public/supplier/interception/view-notice/22785000287?origin=0",
    "page": 1,
    "scraped_at": "2026-03-28T11:33:03.285010"
  },
  {
    "title": "RFI – DND Health Services Supply Chain Logistics Solution",
    "organization": "Department of Public Works and Government Services (PSPC)",
    "published_date": "2026/03/23",
    "closing_date": "2026/04/16",
    "link": "https://www.merx.com/public/supplier/interception/view-notice/22785000213?origin=0",
    "page": 1,
    "scraped_at": "2026-03-28T11:33:03.435141"
  },
  {
    "title": "IFB 2613AM Millard Health Roof Replacement 2026",
    "organization": "Workers' Compensation Board of Alberta",
    "published_date": "2026/03/25",
    "closing_date": "2026/04/20",
    "link": "https://www.merx.com/public/supplier/interception/view-notice/443939422054?origin=0",
    "page": 1,
    "scraped_at": "2026-03-28T11:33:03.461133"
  },
  {
    "title": "Leased Residential Housing for Newfoundland and Labrador Health Services (NLHS)",
    "organization": "NL Provincial Health Shared Services Supply Chain",
    "published_date": "2026/03/26",
    "closing_date": "2026/04/09",
    "link": "https://www.merx.com/govnl/solicitations/open-bids/Leased-Residential-Housing-for-Newfoundland-and-Labrador-Health-Services-NLHS/0000318565?origin=0",
    "page": 1,
    "scraped_at": "2026-03-28T11:33:03.513253"
  },
  {
    "title": "Sanirajak Health Centre Exterior Ramp & Interior Accessibility Upgrades Sanirajak, NU",
    "organization": "Government of Nunavut",
    "published_date": "2026/03/24",
    "closing_date": "2026/04/15",
    "link": "https://www.merx.com/public/supplier/interception/view-notice/443937045947?origin=0",
    "page": 2,
    "scraped_at": "2026-03-28T11:33:15.548237"
  },
  {
    "title": "Electronic Health Record Platform (EHRP) Project Management Support Services (PMSS)",
    "organization": "Department of National Defence (DND)",
    "published_date": "2026/03/26",
    "closing_date": "2026/05/08",
    "link": "https://www.merx.com/public/supplier/interception/view-notice/22785000558?origin=0",
    "page": 2,
    "scraped_at": "2026-03-28T11:33:15.574243"
  },
  {
    "title": "E580-00 Surrey North Delta PCN – Long Term",
    "organization": "Fraser Health Authority",
    "published_date": "2026/03/26",
    "closing_date": "2026/04/15",
    "link": "https://www.merx.com/public/supplier/interception/view-notice/443940645842?origin=0",
    "page": 2,
    "scraped_at": "2026-03-28T11:33:16.094768"
  },
  {
    "title": "FRASER LAKE - Chiller Replacement RFP",
    "organization": "Northern Health Authority",
    "published_date": "2026/03/26",
    "closing_date": "2026/04/23",
    "link": "https://www.merx.com/public/supplier/interception/view-notice/443940685006?origin=0",
    "page": 2,
    "scraped_at": "2026-03-28T11:33:16.120362"
  },
  {
    "title": "K103-00 RMH North Acute Tower Roof Replacement",
    "organization": "Fraser Health Authority",
    "published_date": "2026/03/26",
    "closing_date": "2026/04/15",
    "link": "https://www.merx.com/public/supplier/interception/view-notice/443940645831?origin=0",
    "page": 3,
    "scraped_at": "2026-03-28T11:33:27.969430"
  },
  {
    "title": "K102-00 MMH Northwest Acute Tower Roof Replacement",
    "organization": "Fraser Health Authority",
    "published_date": "2026/03/26",
    "closing_date": "2026/04/14",
    "link": "https://www.merx.com/public/supplier/interception/view-notice/443940645836?origin=0",
    "page": 3,
    "scraped_at": "2026-03-28T11:33:27.995870"
  },
  {
    "title": "E580-00 Surrey North Delta PCN – Long Term",
    "organization": "Fraser Health Authority",
    "published_date": "2026/03/26",
    "closing_date": "2026/04/15",
    "link": "https://www.merx.com/public/supplier/interception/view-notice/443940645842?origin=0",
    "page": 3,
    "scraped_at": "2026-03-28T11:33:28.077210"
  },
  {
    "title": "FRASER LAKE - Chiller Replacement RFP",
    "organization": "Northern Health Authority",
    "published_date": "2026/03/26",
    "closing_date": "2026/04/23",
    "link": "https://www.merx.com/public/supplier/interception/view-notice/443940685006?origin=0",
    "page": 3,
    "scraped_at": "2026-03-28T11:33:28.104963"
  },
  {
    "title": "Pharmacy Services for Kamsack Hospital and District Nursing Home",
    "organization": "Saskatchewan Health Authority",
    "published_date": "2026/03/26",
    "closing_date": "2026/04/15",
    "link": "https://www.merx.com/public/supplier/interception/view-notice/443941271810?origin=0",
    "page": 3,
    "scraped_at": "2026-03-28T11:33:28.133048"
  },
  {
    "title": "RFI-2026-03-20-1MH",
    "organization": "Northern Health Authority",
    "published_date": "RFI-2026-03-20-1MH",
    "closing_date": "2026/03/23",
    "link": "https://www.merx.com/public/supplier/interception/view-notice/443936159542?origin=0",
    "page": 3,
    "scraped_at": "2026-03-28T11:33:28.271862"
  },
  {
    "title": "West Nile Virus Mosquito Identification and Viral Testing Program",
    "organization": "Grand Erie Public Health",
    "published_date": "2026/03/23",
    "closing_date": "2026/04/17",
    "link": "https://www.merx.com/solicitations/open-bids/West-Nile-Virus-Mosquito-Identification-and-Viral-Testing-Program/0000318203?origin=0",
    "page": 3,
    "scraped_at": "2026-03-28T11:33:28.381727"
  },
  {
    "title": "RFI-2026-03-20-CRE",
    "organization": "Northern Health Authority",
    "published_date": "RFI-2026-03-20-CRE",
    "closing_date": "2026/03/23",
    "link": "https://www.merx.com/public/supplier/interception/view-notice/443936159505?origin=0",
    "page": 3,
    "scraped_at": "2026-03-28T11:33:28.409103"
  },
  {
    "title": "RFI-2026-03-20-QUE Residential Tenancy Agreement",
    "organization": "Northern Health Authority",
    "published_date": "2026/03/23",
    "closing_date": "2026/03/30",
    "link": "https://www.merx.com/public/supplier/interception/view-notice/443936159545?origin=0",
    "page": 3,
    "scraped_at": "2026-03-28T11:33:28.436529"
  },
  {
    "title": "TERRACE - Withdrawal Management Facility Planning RFP",
    "organization": "Northern Health Authority",
    "published_date": "2026/03/24",
    "closing_date": "2026/04/28",
    "link": "https://www.merx.com/public/supplier/interception/view-notice/443937386256?origin=0",
    "page": 3,
    "scraped_at": "2026-03-28T11:33:28.474779"
  },
  {
    "title": "2026 Open & Ongoing RFPQ",
    "organization": "Fraser Health Authority",
    "published_date": "2026 Open & Ongoing RFPQ",
    "closing_date": "2026/01/27",
    "link": "https://www.merx.com/public/supplier/interception/view-notice/443846879064?origin=0",
    "page": 3,
    "scraped_at": "2026-03-28T11:33:28.528442"
  },
  {
    "title": "K102-00 MMH Northwest Acute Tower Roof Replacement",
    "organization": "Fraser Health Authority",
    "published_date": "2026/03/25",
    "closing_date": "2026/04/14",
    "link": "https://www.merx.com/public/supplier/interception/view-notice/443939118573?origin=0",
    "page": 3,
    "scraped_at": "2026-03-28T11:33:28.608127"
  },
  {
    "title": "Financial Audit Services",
    "organization": "North Bay Regional Health Centre",
    "published_date": "2026/03/23",
    "closing_date": "2026/04/22",
    "link": "https://www.merx.com/solicitations/open-bids/Financial-Audit-Services/0000318227?origin=0",
    "page": 4,
    "scraped_at": "2026-03-28T11:33:40.587218"
  },
  {
    "title": "002NOI26AS: F493-00 LGH Vault-B Renewal",
    "organization": "Vancouver Coastal Health Authority",
    "published_date": "2026/03/23",
    "closing_date": "2026/03/30",
    "link": "https://www.merx.com/public/supplier/interception/view-notice/443936159548?origin=0",
    "page": 4,
    "scraped_at": "2026-03-28T11:33:40.612422"
  },
  {
    "title": "727 Fisgard Office Reno - Construction Manager",
    "organization": "Vancouver Island Health Authority",
    "published_date": "2026/03/27",
    "closing_date": "2026/04/24",
    "link": "https://www.merx.com/public/supplier/interception/view-notice/443942456162?origin=0",
    "page": 4,
    "scraped_at": "2026-03-28T11:33:40.638050"
  },
  {
    "title": "SU27TAS7204 - Regen and Forest Health Surveys in the Morice and Bulkley Operating Areas of the Babine Business Area",
    "organization": "BC Timber Sales",
    "published_date": "2026/03/27",
    "closing_date": "2026/04/22",
    "link": "https://www.merx.com/public/supplier/interception/view-notice/443942456158?origin=0",
    "page": 4,
    "scraped_at": "2026-03-28T11:33:40.793444"
  },
  {
    "title": "ITQ PHSA 18728 UV Sanitizer for Laundry Carts",
    "organization": "Provincial Health Services Authority BC",
    "published_date": "2026/03/25",
    "closing_date": "2026/04/15",
    "link": "https://www.merx.com/public/supplier/interception/view-notice/443939065228?origin=0",
    "page": 4,
    "scraped_at": "2026-03-28T11:33:40.871416"
  },
  {
    "title": "PHSA 16633 Ultrasound Systems",
    "organization": "Provincial Health Services Authority BC",
    "published_date": "PHSA 16633 Ultrasound Systems",
    "closing_date": "2026/03/11",
    "link": "https://www.merx.com/public/supplier/interception/view-notice/443917264391?origin=0",
    "page": 4,
    "scraped_at": "2026-03-28T11:33:40.923050"
  },
  {
    "title": "Leased Ambulance Fleet Centre and Base – St. John’s Metro Area, NL",
    "organization": "NL Provincial Health Shared Services Supply Chain",
    "published_date": "2026/03/24",
    "closing_date": "2026/04/23",
    "link": "https://www.merx.com/govnl/solicitations/open-bids/Leased-Ambulance-Fleet-Centre-and-Base-St-John-s-Metro-Area-NL/0000318300?origin=0",
    "page": 4,
    "scraped_at": "2026-03-28T11:33:41.045948"
  },
  {
    "title": "Design and Manufacture Power Distribution",
    "organization": "Department of Public Works and Government Services (PSPC)",
    "published_date": "2026/03/23",
    "closing_date": "2026/04/07",
    "link": "https://www.merx.com/public/supplier/interception/view-notice/22785000249?origin=0",
    "page": 4,
    "scraped_at": "2026-03-28T11:33:41.123276"
  },
  {
    "title": "6D063-247552 System 800xA Update",
    "organization": "Department of Public Works and Government Services (PSPC)",
    "published_date": "2026/03/24",
    "closing_date": "2026/04/22",
    "link": "https://www.merx.com/public/supplier/interception/view-notice/22785000470?origin=0",
    "page": 5,
    "scraped_at": "2026-03-28T11:33:53.118477"
  },
  {
    "title": "TA2201 - TFL30",
    "organization": "BC Timber Sales - Timber Auctions",
    "published_date": "TA2201 - TFL30",
    "closing_date": "2026/03/20",
    "link": "https://www.merx.com/public/supplier/interception/view-notice/443932097919?origin=0",
    "page": 5,
    "scraped_at": "2026-03-28T11:33:53.475634"
  },
  {
    "title": "TA2516 - Walker",
    "organization": "BC Timber Sales - Timber Auctions",
    "published_date": "TA2516 - Walker",
    "closing_date": "2026/03/10",
    "link": "https://www.merx.com/public/supplier/interception/view-notice/443915446318?origin=0",
    "page": 5,
    "scraped_at": "2026-03-28T11:33:53.503024"
  },
  {
    "title": "TA1496 - Reynolds",
    "organization": "BC Timber Sales - Timber Auctions",
    "published_date": "TA1496 - Reynolds",
    "closing_date": "2026/03/20",
    "link": "https://www.merx.com/public/supplier/interception/view-notice/443932181063?origin=0",
    "page": 5,
    "scraped_at": "2026-03-28T11:33:53.529801"
  },
  {
    "title": "TA1562 - Skeena West",
    "organization": "BC Timber Sales - Timber Auctions",
    "published_date": "TA1562 - Skeena West",
    "closing_date": "2026/03/27",
    "link": "https://www.merx.com/public/supplier/interception/view-notice/443942574304?origin=0",
    "page": 5,
    "scraped_at": "2026-03-28T11:33:53.575316"
  },
  {
    "title": "TSL TA2565-B, TPL - DC, Wolverine",
    "organization": "BC Timber Sales - Timber Auctions",
    "published_date": "2026/03/26",
    "closing_date": "2026/04/22",
    "link": "https://www.merx.com/public/supplier/interception/view-notice/443940600778?origin=0",
    "page": 5,
    "scraped_at": "2026-03-28T11:33:53.654269"
  },
  {
    "title": "A95019, TPL - DC, Redwillow",
    "organization": "BC Timber Sales - Timber Auctions",
    "published_date": "A95019, TPL - DC, Redwillow",
    "closing_date": "2026/03/12",
    "link": "https://www.merx.com/public/supplier/interception/view-notice/443919365439?origin=0",
    "page": 5,
    "scraped_at": "2026-03-28T11:33:53.681714"
  },
  {
    "title": "TA2901 - Akie/Del",
    "organization": "BC Timber Sales - Timber Auctions",
    "published_date": "TA2901 - Akie/Del",
    "closing_date": "2026/03/17",
    "link": "https://www.merx.com/public/supplier/interception/view-notice/443927317812?origin=0",
    "page": 5,
    "scraped_at": "2026-03-28T11:33:53.708395"
  },
  {
    "title": "TA2333 - Avola - Kamloops TSA(Clearwater)",
    "organization": "BC Timber Sales - Timber Auctions",
    "published_date": "2026/03/23",
    "closing_date": "2026/04/09",
    "link": "https://www.merx.com/public/supplier/interception/view-notice/443936159512?origin=0",
    "page": 5,
    "scraped_at": "2026-03-28T11:33:53.735517"
  }
]